pyMSVC/__init__.py
pyMSVC/vswhere.py
pymsvc-0.6.1.dist-info/licenses/LICENSE
pymsvc-0.6.1.dist-info/METADATA
pymsvc-0.6.1.dist-info/WHEEL
pymsvc-0.6.1.dist-info/top_level.txt
pymsvc-0.6.1.dist-info/RECORD
