Metadata-Version: 2.4
Name: pyMSVC
Version: 0.6.1
Summary: Simple to use MSVC build environment setup tool.
Author: Kevin Schlosser
License: ***********************************************************************************
Project-URL: Homepage, https://github.com/kdschlosser/python_msvc
Project-URL: Issues, https://github.com/kdschlosser/python_msvc/issues
Classifier: Development Status :: 5 - Production/Stable
Classifier: Environment :: Win32 (MS Windows)
Classifier: Framework :: Setuptools Plugin
Classifier: Intended Audience :: Developers
Classifier: License :: OSI Approved :: MIT License
Classifier: Natural Language :: English
Classifier: Programming Language :: Python :: 3 :: Only
Classifier: Programming Language :: Python :: 3.8
Classifier: Programming Language :: Python :: 3.9
Classifier: Programming Language :: Python :: 3.10
Classifier: Programming Language :: Python :: 3.11
Classifier: Programming Language :: Python :: 3.12
Classifier: Programming Language :: Python :: 3.13
Classifier: Programming Language :: Cython
Classifier: Programming Language :: C
Classifier: Programming Language :: C++
Classifier: Programming Language :: C#
Classifier: Programming Language :: F#
Classifier: Programming Language :: Python :: Free Threading
Classifier: Operating System :: Microsoft :: Windows
Classifier: Operating System :: Microsoft :: Windows :: Windows 7
Classifier: Operating System :: Microsoft :: Windows :: Windows 8
Classifier: Operating System :: Microsoft :: Windows :: Windows 8.1
Classifier: Operating System :: Microsoft :: Windows :: Windows 10
Classifier: Operating System :: Microsoft :: Windows :: Windows 11
Classifier: Topic :: Software Development :: Build Tools
Classifier: Topic :: Software Development :: Compilers
Requires-Python: >=3.6
License-File: LICENSE
Requires-Dist: comtypes==1.4.13
Dynamic: license-file
